pypwdless/__init__.py
pypwdless/config.py
pypwdless/pwdless.py
pypwdless-1.0.dist-info/METADATA
pypwdless-1.0.dist-info/RECORD
pypwdless-1.0.dist-info/WHEEL
pypwdless-1.0.dist-info/top_level.txt
