Metadata-Version: 2.1
Name: pypwdless
Version: 1.0
Summary: Password less authentication in Python
Home-page: https://github.com/narayan8291/pypwdless
Author: Narayan Gowraj
Author-email: gowrajn@gmail.com
License: MIT
Platform: UNKNOWN
Requires-Dist: PyJWT
